[
  {
    "step": "exact_dedup",
    "merged_into": "发动机安全管理系统",
    "merged_from": "发动机安全管理系统"
  },
  {
    "step": "exact_dedup",
    "merged_into": "发动机安全管理系统_发动机",
    "merged_from": "发动机安全管理系统_发动机"
  },
  {
    "step": "exact_dedup",
    "merged_into": "发动机安全管理系统_电池",
    "merged_from": "发动机安全管理系统_电池"
  },
  {
    "step": "exact_dedup",
    "merged_into": "发动机安全管理系统",
    "merged_from": "发动机安全管理系统"
  },
  {
    "step": "exact_dedup",
    "merged_into": "发动机安全管理系统_发动机",
    "merged_from": "发动机安全管理系统_发动机"
  },
  {
    "step": "exact_dedup",
    "merged_into": "发动机安全管理系统_润滑系统",
    "merged_from": "发动机安全管理系统_润滑系统"
  },
  {
    "step": "exact_dedup",
    "merged_into": "发动机安全管理系统",
    "merged_from": "发动机安全管理系统"
  },
  {
    "step": "exact_dedup",
    "merged_into": "发动机安全管理系统_燃油系统",
    "merged_from": "发动机安全管理系统_燃油系统"
  },
  {
    "step": "exact_dedup",
    "merged_into": "发动机安全管理系统_发动机",
    "merged_from": "发动机安全管理系统_发动机"
  },
  {
    "step": "exact_dedup",
    "merged_into": "发动机安全管理系统_燃油系统_燃油过滤器",
    "merged_from": "发动机安全管理系统_燃油系统_燃油过滤器"
  },
  {
    "step": "exact_dedup",
    "merged_into": "发动机安全管理系统_燃油系统_手泵",
    "merged_from": "发动机安全管理系统_燃油系统_手泵"
  },
  {
    "step": "exact_dedup",
    "merged_into": "发动机安全管理系统_发动机_涡轮增压器",
    "merged_from": "发动机安全管理系统_发动机_涡轮增压器"
  },
  {
    "step": "exact_dedup",
    "merged_into": "发动机安全管理系统_人身伤害风险",
    "merged_from": "发动机安全管理系统_人身伤害风险"
  },
  {
    "step": "exact_dedup",
    "merged_into": "发动机安全管理系统_火灾爆炸风险",
    "merged_from": "发动机安全管理系统_火灾爆炸风险"
  },
  {
    "step": "exact_dedup",
    "merged_into": "发动机安全管理系统_发动机",
    "merged_from": "发动机安全管理系统_发动机"
  },
  {
    "step": "exact_dedup",
    "merged_into": "发动机安全管理系统_冷却系统",
    "merged_from": "发动机安全管理系统_冷却系统"
  },
  {
    "step": "exact_dedup",
    "merged_into": "发动机安全管理系统_发动机_传动皮带",
    "merged_from": "发动机安全管理系统_发动机_传动皮带"
  },
  {
    "step": "exact_dedup",
    "merged_into": "发动机安全管理系统_冷却系统_叶轮泵",
    "merged_from": "发动机安全管理系统_冷却系统_叶轮泵"
  },
  {
    "step": "exact_dedup",
    "merged_into": "发动机安全管理系统_冷却系统_加满冷却剂",
    "merged_from": "发动机安全管理系统_冷却系统_加满冷却剂"
  },
  {
    "step": "exact_dedup",
    "merged_into": "发动机安全管理系统_冷却系统_膨胀箱",
    "merged_from": "发动机安全管理系统_冷却系统_膨胀箱"
  },
  {
    "step": "exact_dedup",
    "merged_into": "Marine Engine System",
    "merged_from": "Marine Engine System"
  },
  {
    "step": "exact_dedup",
    "merged_into": "Marine Engine System_Fuel System",
    "merged_from": "Marine Engine System_Fuel System"
  },
  {
    "step": "exact_dedup",
    "merged_into": "Marine Engine System_Cooling System",
    "merged_from": "Marine Engine System_Cooling System"
  },
  {
    "step": "exact_dedup",
    "merged_into": "Marine Engine System_Lubrication System",
    "merged_from": "Marine Engine System_Lubrication System"
  },
  {
    "step": "exact_dedup",
    "merged_into": "Marine Engine System_Engine Control Module",
    "merged_from": "Marine Engine System_Engine Control Module"
  },
  {
    "step": "exact_dedup",
    "merged_into": "Marine Engine System",
    "merged_from": "Marine Engine System"
  },
  {
    "step": "exact_dedup",
    "merged_into": "Marine Engine System_Trip Computer",
    "merged_from": "Marine Engine System_Trip Computer"
  },
  {
    "step": "exact_dedup",
    "merged_into": "Marine Engine System_Warning Management Program",
    "merged_from": "Marine Engine System_Warning Management Program"
  },
  {
    "step": "exact_dedup",
    "merged_into": "FaultPhenomenon_Speedometer Error",
    "merged_from": "FaultPhenomenon_Speedometer Error"
  },
  {
    "step": "exact_dedup",
    "merged_into": "FaultCause_Speed Factor Mismatch",
    "merged_from": "FaultCause_Speed Factor Mismatch"
  },
  {
    "step": "exact_dedup",
    "merged_into": "Marine Engine System",
    "merged_from": "Marine Engine System"
  },
  {
    "step": "exact_dedup",
    "merged_into": "Marine Engine System_Electrical System",
    "merged_from": "Marine Engine System_Electrical System"
  },
  {
    "step": "exact_dedup",
    "merged_into": "Marine Engine System_External Steering",
    "merged_from": "Marine Engine System_External Steering"
  },
  {
    "step": "exact_dedup",
    "merged_into": "Marine Engine System_Glass Cockpit Display",
    "merged_from": "Marine Engine System_Glass Cockpit Display"
  },
  {
    "step": "exact_dedup",
    "merged_into": "Marine Engine System_Warning Management Program",
    "merged_from": "Marine Engine System_Warning Management Program"
  },
  {
    "step": "exact_dedup",
    "merged_into": "FaultPhenomenon_Engine Overspeed",
    "merged_from": "FaultPhenomenon_Engine Overspeed"
  },
  {
    "step": "exact_dedup",
    "merged_into": "FaultPhenomenon_Mechanical Damage",
    "merged_from": "FaultPhenomenon_Mechanical Damage"
  },
  {
    "step": "exact_dedup",
    "merged_into": "Marine Engine System_Joystick",
    "merged_from": "Marine Engine System_Joystick"
  },
  {
    "step": "exact_dedup",
    "merged_into": "Marine Engine System_Autopilot",
    "merged_from": "Marine Engine System_Autopilot"
  },
  {
    "step": "exact_dedup",
    "merged_into": "Marine Engine System_Glass Cockpit Display",
    "merged_from": "Marine Engine System_Glass Cockpit Display"
  },
  {
    "step": "exact_dedup",
    "merged_into": "Marine Engine System_External Steering",
    "merged_from": "Marine Engine System_External Steering"
  },
  {
    "step": "exact_dedup",
    "merged_into": "FaultPhenomenon_Mechanical Damage",
    "merged_from": "FaultPhenomenon_Mechanical Damage"
  },
  {
    "step": "exact_dedup",
    "merged_into": "Marine Engine System",
    "merged_from": "Marine Engine System"
  },
  {
    "step": "exact_dedup",
    "merged_into": "Marine Engine System",
    "merged_from": "Marine Engine System"
  },
  {
    "step": "exact_dedup",
    "merged_into": "FaultPhenomenon_Mechanical Damage",
    "merged_from": "FaultPhenomenon_Mechanical Damage"
  },
  {
    "step": "exact_dedup",
    "merged_into": "FaultPhenomenon_Shortened Engine Life",
    "merged_from": "FaultPhenomenon_Shortened Engine Life"
  },
  {
    "step": "exact_dedup",
    "merged_into": "Marine Engine System_Engine Control Module",
    "merged_from": "Marine Engine System_Engine Control Module"
  },
  {
    "step": "exact_dedup",
    "merged_into": "Marine Engine System_Information Display",
    "merged_from": "Marine Engine System_Information Display"
  },
  {
    "step": "exact_dedup",
    "merged_into": "DiagnosticMethod_Check Fault Code",
    "merged_from": "DiagnosticMethod_Check Fault Code"
  },
  {
    "step": "exact_dedup",
    "merged_into": "Marine Engine System_Alternator",
    "merged_from": "Marine Engine System_Alternator"
  },
  {
    "step": "exact_dedup",
    "merged_into": "Marine Engine System_Echo Sounder",
    "merged_from": "Marine Engine System_Echo Sounder"
  },
  {
    "step": "exact_dedup",
    "merged_into": "Marine Engine System_Lubrication System",
    "merged_from": "Marine Engine System_Lubrication System"
  },
  {
    "step": "exact_dedup",
    "merged_into": "Marine Engine System_Joystick",
    "merged_from": "Marine Engine System_Joystick"
  },
  {
    "step": "exact_dedup",
    "merged_into": "Marine Engine System_Docking Mode",
    "merged_from": "Marine Engine System_Docking Mode"
  },
  {
    "step": "exact_dedup",
    "merged_into": "Marine Engine System_Stern Drive",
    "merged_from": "Marine Engine System_Stern Drive"
  },
  {
    "step": "exact_dedup",
    "merged_into": "Marine Engine System_Cooling System",
    "merged_from": "Marine Engine System_Cooling System"
  },
  {
    "step": "exact_dedup",
    "merged_into": "Marine Engine System_Glass Cockpit Display",
    "merged_from": "Marine Engine System_Glass Cockpit Display"
  },
  {
    "step": "exact_dedup",
    "merged_into": "Marine Engine System_Parameter_Neutral Warning Sound",
    "merged_from": "Marine Engine System_Parameter_Neutral Warning Sound"
  },
  {
    "step": "exact_dedup",
    "merged_into": "Volvo Penta Engine",
    "merged_from": "Volvo Penta Engine"
  },
  {
    "step": "exact_dedup",
    "merged_into": "Volvo Penta Engine_Transmission System_Propeller Shaft",
    "merged_from": "Volvo Penta Engine_Transmission System_Propeller Shaft"
  },
  {
    "step": "exact_dedup",
    "merged_into": "Volvo Penta Engine_Transmission System_Transmission Malfunction",
    "merged_from": "Volvo Penta Engine_Transmission System_Transmission Malfunction"
  },
  {
    "step": "exact_dedup",
    "merged_into": "Volvo Penta Engine_Steering System_Electric Steering Unit",
    "merged_from": "Volvo Penta Engine_Steering System_Electric Steering Unit"
  },
  {
    "step": "exact_dedup",
    "merged_into": "Volvo Penta Engine_Steering System_Dipstick",
    "merged_from": "Volvo Penta Engine_Steering System_Dipstick"
  },
  {
    "step": "exact_dedup",
    "merged_into": "Volvo Penta Engine",
    "merged_from": "Volvo Penta Engine"
  },
  {
    "step": "exact_dedup",
    "merged_into": "Volvo Penta Engine_Mechanical System",
    "merged_from": "Volvo Penta Engine_Mechanical System"
  },
  {
    "step": "exact_dedup",
    "merged_into": "Volvo Penta Engine_Cooling System",
    "merged_from": "Volvo Penta Engine_Cooling System"
  },
  {
    "step": "exact_dedup",
    "merged_into": "Volvo Penta Engine_Electrical System_Alternator",
    "merged_from": "Volvo Penta Engine_Electrical System_Alternator"
  },
  {
    "step": "exact_dedup",
    "merged_into": "Volvo Penta Engine_Electrical System_Battery",
    "merged_from": "Volvo Penta Engine_Electrical System_Battery"
  },
  {
    "step": "label_unify",
    "name": "Marine Engine System_Battery",
    "labels_merged": [
      "Component",
      "Equipment"
    ]
  },
  {
    "step": "label_unify",
    "name": "Marine Engine System_Fuel System",
    "labels_merged": [
      "Component",
      "System"
    ]
  },
  {
    "step": "label_unify",
    "name": "Marine Engine System_Cooling System",
    "labels_merged": [
      "Component",
      "System"
    ]
  },
  {
    "step": "label_unify",
    "name": "Marine Engine System_Lubrication System",
    "labels_merged": [
      "Component",
      "System"
    ]
  },
  {
    "step": "semantic_merge",
    "entity_a": "Volvo Penta Engine_Fault_Fuel Leak",
    "entity_b": "Volvo Penta Engine_Fault_Coolant Leak",
    "label": "FaultPhenomenon",
    "threshold": 0.93,
    "similarity": 0.9458
  },
  {
    "step": "semantic_merge",
    "entity_a": "Volvo Penta Engine_Fault_Fuel Leak",
    "entity_b": "Volvo Penta Engine_Fault_Oil Leak",
    "label": "FaultPhenomenon",
    "threshold": 0.93,
    "similarity": 0.9744
  },
  {
    "step": "semantic_merge",
    "entity_a": "Marine Engine System_FaultCause_Air In Fuel System",
    "entity_b": "Marine Engine System_FaultCause_Water In Fuel",
    "label": "FaultCause",
    "threshold": 0.93,
    "similarity": 0.9332
  },
  {
    "step": "semantic_merge",
    "entity_a": "发动机安全管理系统_燃油系统_清洁度要求",
    "entity_b": "发动机安全管理系统_发动机_清洁度要求",
    "label": "SafetyNote",
    "threshold": 0.92,
    "similarity": 0.9534
  },
  {
    "step": "semantic_merge",
    "entity_a": "发动机安全管理系统_冷却系统_冷却剂规格要求",
    "entity_b": "发动机安全管理系统_冷却系统_冷却剂混合要求",
    "label": "SafetyNote",
    "threshold": 0.92,
    "similarity": 0.9318
  },
  {
    "step": "semantic_merge",
    "entity_a": "Volvo Penta Engine_Safety_Hot Coolant Burn Risk",
    "entity_b": "Volvo Penta Engine_Safety_Hot Oil Burn Risk",
    "label": "SafetyNote",
    "threshold": 0.92,
    "similarity": 0.9505
  },
  {
    "step": "semantic_merge",
    "entity_a": "Volvo Penta Engine_Cooling System_Anode Cleaning Restriction",
    "entity_b": "Volvo Penta Engine_Transmission System_Anode Cleaning Restriction",
    "label": "SafetyNote",
    "threshold": 0.92,
    "similarity": 0.9575
  },
  {
    "step": "semantic_merge",
    "entity_a": "Volvo Penta Engine_Transmission System_Exhaust Plate Cleaning Restriction",
    "entity_b": "Volvo Penta Engine_Transmission System_Exhaust Plate Painting Restriction",
    "label": "SafetyNote",
    "threshold": 0.92,
    "similarity": 0.9296
  },
  {
    "step": "semantic_merge",
    "entity_a": "Volvo Penta Engine_Transmission System_Dipstick Material Warning",
    "entity_b": "Volvo Penta Engine_Transmission System_Dipstick Plastic Warning",
    "label": "SafetyNote",
    "threshold": 0.92,
    "similarity": 0.9487
  },
  {
    "step": "semantic_merge",
    "entity_a": "Marine Engine System_Parameter_Oil Viscosity",
    "entity_b": "Marine Engine System_Parameter_Fuel Viscosity",
    "label": "Parameter",
    "threshold": 0.95,
    "similarity": 0.9568
  },
  {
    "step": "semantic_merge",
    "entity_a": "Volvo Penta Engine_Lubrication System_Oil Level Check",
    "entity_b": "Volvo Penta Engine_Transmission System_Oil Level Check",
    "label": "DiagnosticMethod",
    "threshold": 0.92,
    "similarity": 0.9633
  },
  {
    "step": "semantic_merge",
    "entity_a": "Volvo Penta Engine_Lubrication System_Oil Level Check",
    "entity_b": "Volvo Penta Engine_Steering System_Steering Oil Level Check",
    "label": "DiagnosticMethod",
    "threshold": 0.92,
    "similarity": 0.9225
  },
  {
    "step": "semantic_merge",
    "entity_a": "发动机安全管理系统_燃油系统_过滤器排气",
    "entity_b": "发动机安全管理系统_燃油系统_过滤器更换",
    "label": "RepairMethod",
    "threshold": 0.92,
    "similarity": 0.9461
  },
  {
    "step": "semantic_merge",
    "entity_a": "发动机安全管理系统_燃油系统_过滤器排气",
    "entity_b": "发动机安全管理系统_燃油系统_系统排气",
    "label": "RepairMethod",
    "threshold": 0.92,
    "similarity": 0.9411
  },
  {
    "step": "semantic_merge",
    "entity_a": "发动机安全管理系统_冷却系统_加满冷却剂",
    "entity_b": "发动机安全管理系统_冷却系统_清空冷却剂",
    "label": "RepairMethod",
    "threshold": 0.92,
    "similarity": 0.9221
  },
  {
    "step": "semantic_merge",
    "entity_a": "发动机安全管理系统_冷却系统_清空冷却剂",
    "entity_b": "发动机安全管理系统_冷却系统_冲洗冷却系统",
    "label": "RepairMethod",
    "threshold": 0.92,
    "similarity": 0.929
  },
  {
    "step": "semantic_merge",
    "entity_a": "发动机安全管理系统_冷却系统_更换叶轮",
    "entity_b": "发动机安全管理系统_冷却系统_拆卸叶轮储存",
    "label": "RepairMethod",
    "threshold": 0.92,
    "similarity": 0.9201
  },
  {
    "step": "semantic_merge",
    "entity_a": "Volvo Penta Engine_Repair_Engine Overhaul",
    "entity_b": "Volvo Penta Engine_Transmission System_Overhaul",
    "label": "RepairMethod",
    "threshold": 0.92,
    "similarity": 0.9371
  },
  {
    "step": "semantic_merge",
    "entity_a": "Volvo Penta Engine_Lubrication System_Oil And Filter Replacement",
    "entity_b": "Volvo Penta Engine_Transmission System_Oil Filter Replacement",
    "label": "RepairMethod",
    "threshold": 0.92,
    "similarity": 0.942
  },
  {
    "step": "semantic_merge",
    "entity_a": "Volvo Penta Engine_Cooling System_Anode Replacement",
    "entity_b": "Volvo Penta Engine_Transmission System_Anode Replacement",
    "label": "RepairMethod",
    "threshold": 0.92,
    "similarity": 0.9389
  }
]